__init__.py
amf_fast_inference/__init__.py
amf_fast_inference/model.py
amf_fast_inference-0.0.3.dist-info/METADATA
amf_fast_inference-0.0.3.dist-info/WHEEL
amf_fast_inference-0.0.3.dist-info/top_level.txt
amf_fast_inference-0.0.3.dist-info/RECORD
